README.txt
setup.cfg
setup.py
translationstring/__init__.py
translationstring/compat.py
translationstring.egg-info/PKG-INFO
translationstring.egg-info/SOURCES.txt
translationstring.egg-info/dependency_links.txt
translationstring.egg-info/not-zip-safe
translationstring.egg-info/top_level.txt
translationstring/tests/__init__.py
translationstring/tests/test__init__.py
translationstring/tests/test_integration.py
translationstring/tests/translations.py