Metadata-Version: 1.0
Name: translationstring
Version: 1.0
Summary: Utility library for i18n relied on by various Repoze and Pyramid packages
Home-page: http://pylonsproject.org
Author: Chris McDonough, Agendaless Consulting
Author-email: pylons-discuss@googlegroups.com
License: BSD-like (http://repoze.org/license.html)
Keywords: i18n l10n internationalization localization gettext chameleon
Platform: UNKNOWN
Classifier: Development Status :: 5 - Production/Stable
Classifier: Intended Audience :: Developers
Classifier: Programming Language :: Python :: 2
Classifier: Programming Language :: Python :: 2.4
Classifier: Programming Language :: Python :: 2.5
Classifier: Programming Language :: Python :: 2.6
Classifier: Programming Language :: Python :: 2.7
Classifier: Programming Language :: Python :: 3
Classifier: Programming Language :: Python :: 3.2
Classifier: Topic :: Software Development :: Libraries :: Python Modules
Classifier: Topic :: Software Development :: Internationalization
Classifier: Topic :: Software Development :: Localization
